pytest_jupyterhub/__init__.py
pytest_jupyterhub/_version.py
pytest_jupyterhub/jupyterhub_spawners.py
pytest_jupyterhub-0.1.0.dist-info/METADATA
pytest_jupyterhub-0.1.0.dist-info/WHEEL
pytest_jupyterhub-0.1.0.dist-info/entry_points.txt
pytest_jupyterhub-0.1.0.dist-info/licenses/LICENSE
pytest_jupyterhub-0.1.0.dist-info/RECORD
