Metadata-Version: 2.1
Name: pytest-jupyterhub
Version: 0.1.0
Summary: A reusable JupyterHub pytest plugin
Project-URL: Documentation, https://pytest-jupyterhub.readthedocs.io
Project-URL: Source, https://github.com/jupyterhub/pytest-jupyterhub
Project-URL: Issues, https://github.com/jupyterhub/pytest-jupyterhub/issues
Author-email: Jupyter Contributors <jupyter@googlegroups.com>
License: BSD 3-Clause License
License-File: LICENSE
Keywords: jupyterhub,plugin,pytest
Classifier: Development Status :: 5 - Production/Stable
Classifier: Framework :: Pytest
Classifier: Programming Language :: Python :: 3
Requires-Python: >=3.8
Requires-Dist: jupyter-server
Requires-Dist: jupyterhub>=2.0.0
Requires-Dist: pytest
Requires-Dist: pytest-asyncio
Provides-Extra: test
Requires-Dist: pytest-asyncio>=0.20.3; extra == 'test'
Requires-Dist: pytest-cov>=4.0.0; extra == 'test'
Requires-Dist: pytest>=7.2.0; extra == 'test'
